bucho/__init__.py
bucho/command.py
bucho/gui.py
bucho/plugins.py
bucho/wsgi.py
bucho-0.1.3.dist-info/METADATA
bucho-0.1.3.dist-info/WHEEL
bucho-0.1.3.dist-info/entry_points.txt
bucho-0.1.3.dist-info/top_level.txt
bucho-0.1.3.dist-info/RECORD
